{
  "Date": "2016-06-10T19:47:34.1861273+07:00",
  "Author": "BokujoMessage4 JSON generated files",
  "Content": [
    {
      "VardId": "MES_LOVE_WITCH_4_00",
      "Text": "<FACE_WITCH><POS_LEFT><FACE_LOSS>\r\nふーむ…。\n新しい魔法の実験がやりたいわ…。"
    },
    {
      "VardId": "MES_LOVE_WITCH_4_01",
      "Text": "<FACE_WITCH><POS_LEFT><FACE_SAD>\r\n<MYNAME>ちゃん\n来てくれないかしら…？"
    },
    {
      "VardId": "MES_LOVE_WITCH_4_02",
      "Text": "<FACE_WITCH><POS_LEFT><FACE_ROUGH>\r\n<MYNAME>ちゃん\nちょうどいいところに！\n待ってたのよ〜♪"
    },
    {
      "VardId": "MES_LOVE_WITCH_4_03",
      "Text": "<FACE_WITCH><POS_LEFT><FACE_LOVE>\r\nねえ、<MYNAME>ちゃん。\nお願いがあるんだけれど…\n引きうけてくれるかしら？"
    },
    {
      "VardId": "MES_LOVE_WITCH_4_04",
      "Text": "魔女さまだからＯＫ"
    },
    {
      "VardId": "MES_LOVE_WITCH_4_05",
      "Text": "何かあやしい…"
    },
    {
      "VardId": "MES_LOVE_WITCH_4_06",
      "Text": "絶対にイヤ"
    },
    {
      "VardId": "MES_LOVE_WITCH_4_07",
      "Text": "牧場にわすれものが…"
    },
    {
      "VardId": "MES_LOVE_WITCH_4_08",
      "Text": "<FACE_WITCH><POS_LEFT><FACE_ROUGH>\r\n何てかわいいことを言ってくれるのかしら。\nうんうん、わたしが見込んだ男の子ねぇ。\n頭をナデナデしてあげるわ。"
    },
    {
      "VardId": "MES_LOVE_WITCH_4_09",
      "Text": "<FACE_WITCH><POS_LEFT><FACE_NORMAL>\r\nお願いごとの内容？\nああ、人体実験に付き合ってほしいのよ。\nなぁに、すぐに終わるわ。"
    },
    {
      "VardId": "MES_LOVE_WITCH_4_10",
      "Text": "<FACE_WITCH><POS_LEFT><FACE_NORMAL>\r\nいいって言ったわよね？"
    },
    {
      "VardId": "MES_LOVE_WITCH_4_11",
      "Text": "<FACE_WITCH><POS_LEFT><FACE_NORMAL>\r\n男に二言はないわよね？"
    },
    {
      "VardId": "MES_LOVE_WITCH_4_12",
      "Text": "<FACE_WITCH><POS_LEFT><FACE_ANGRY>\r\nはっきりしない男はキライよ？"
    },
    {
      "VardId": "MES_LOVE_WITCH_4_13",
      "Text": "<FACE_WITCH><POS_LEFT><FACE_NORMAL>\r\nよしよし、それでいいのよ。\nじゃ、あっちへ行きましょうか。"
    },
    {
      "VardId": "MES_LOVE_WITCH_4_14",
      "Text": "<FACE_WITCH><POS_LEFT><FACE_ROUGH>\r\nほーほっほっほっほ！\nそれじゃ、実験スタートよ♪\nそれっ！"
    },
    {
      "VardId": "MES_LOVE_WITCH_4_15",
      "Text": "<FACE_WITCH><POS_LEFT><FACE_NORMAL>\r\nはい、お疲れ様。\n一通り終わったわよ。"
    },
    {
      "VardId": "MES_LOVE_WITCH_4_16",
      "Text": "<FACE_WITCH><POS_LEFT><FACE_LOSS>\r\nあら？\n顔色悪いわね…。\n大丈夫？"
    },
    {
      "VardId": "MES_LOVE_WITCH_4_17",
      "Text": "<FACE_WITCH><POS_LEFT><FACE_ANGRY>\r\nちょっと、<MYNAME>ちゃん。\nしっかりしなさいよ！\n<MYNAME>ちゃん！"
    },
    {
      "VardId": "MES_LOVE_WITCH_4_18",
      "Text": "<FACE_WITCH><POS_LEFT><FACE_NORMAL>\r\nやっと起きたわね。\nしばらく気絶してたのよ。"
    },
    {
      "VardId": "MES_LOVE_WITCH_4_19",
      "Text": "<FACE_WITCH><POS_LEFT><FACE_SAD>\r\n今回はやりすぎたわ…。\n…ごめんなさい。"
    },
    {
      "VardId": "MES_LOVE_WITCH_4_20",
      "Text": "<FACE_WITCH><POS_LEFT><FACE_ANGRY>\r\nな…何よ。\nわたしだって、悪いと思ったら\nあやまるわよ！"
    },
    {
      "VardId": "MES_LOVE_WITCH_4_21",
      "Text": "<FACE_WITCH><POS_LEFT><FACE_NORMAL>\r\n…よかった、ゆるしてもらえて。\nゆるしてもらえなかったら\n泣いちゃうところだったわ。\n<PAGE>\nそれじゃ、わたしは帰るわね。\nお大事に〜♪"
    },
    {
      "VardId": "MES_LOVE_WITCH_4_22",
      "Text": "<FACE_WITCH><POS_LEFT><FACE_LOSS>\r\nい…いやね。\nそんなわけないじゃない。\nちょっと手伝ってほしいだけよ。\n<PAGE>\nとりあえず、あっちへ行きましょうか。"
    },
    {
      "VardId": "MES_LOVE_WITCH_4_23",
      "Text": "<FACE_WITCH><POS_LEFT><FACE_SAD>\r\nはぁ…。\nあれしきのことで情けないわねぇ。\n<PAGE>\nわたしの恋人でいたいなら、\nもうちょっと、きたえなきゃダメよ？\nあれくらいでへこたれてたら困るわ。"
    },
    {
      "VardId": "MES_LOVE_WITCH_4_24",
      "Text": "<FACE_WITCH><POS_LEFT><FACE_NORMAL>\r\nそうそう、その意気よ♪\nわたしは体力のある人の方が好みなの。\nがんばって♪\n<PAGE>\nそれじゃ、わたしは帰るわね。\nお大事に〜♪"
    },
    {
      "VardId": "MES_LOVE_WITCH_4_25",
      "Text": "<FACE_WITCH><POS_LEFT><FACE_ANGRY>\r\nなんですって！？\n恋人がこんなにお願いしてるのに、\n聞いてくれないわけ？\n<PAGE>\nもういいわよ！！\nとっとと家から出ていけー！"
    },
    {
      "VardId": "MES_LOVE_WITCH_4_26",
      "Text": "<FACE_WITCH><POS_LEFT><FACE_ANGRY>\r\nもー！\nゆるせないわ！！\nせっかく実験しようと思ってたのにー！！"
    },
    {
      "VardId": "MES_LOVE_WITCH_4_27",
      "Text": "<FACE_WITCH><POS_LEFT><FACE_NORMAL>\r\nあら、<MYNAME>ちゃん。\nどこに行くの？"
    },
    {
      "VardId": "MES_LOVE_WITCH_4_28",
      "Text": "<FACE_WITCH><POS_LEFT><FACE_NORMAL>\r\nわすれものなら、\n魔法でとってきてあげるわ。"
    },
    {
      "VardId": "MES_LOVE_WITCH_4_29",
      "Text": "<FACE_WITCH><POS_LEFT><FACE_NORMAL>\r\n何をわすれたのかなぁ？"
    },
    {
      "VardId": "MES_LOVE_WITCH_4_30",
      "Text": "<FACE_WITCH><POS_LEFT><FACE_NORMAL>\r\nよしよし、それでいいのよ。\n…下手なウソはキライよ？\nじゃ、あっちへ行きましょうか。"
    },
    {
      "VardId": "MES_LOVE_WITCH_4_31",
      "Text": "<FACE_WITCH><POS_LEFT><FACE_ANGRY>\r\nわたしにウソをつこうとしたから、\nつい実験に力がはいっちゃった。\n<MYNAME>ちゃんのせいよ？\n<PAGE>\nあんなバレバレのウソつくなんて……。\n魔女とか関係なく、\n恋人ならすぐに分かるわよ。"
    },
    {
      "VardId": "MES_LOVE_WITCH_4_32",
      "Text": "<FACE_WITCH><POS_LEFT><FACE_NORMAL>\r\nこれにこりたら、\n次からはウソはついちゃダメよ？\n<PAGE>\nそれじゃ、わたしは帰るわね。\nお大事に〜♪"
    }
  ]
}