{
  "Date": "2016-06-10T19:47:34.2642571+07:00",
  "Author": "BokujoMessage4 JSON generated files",
  "Content": [
    {
      "VardId": "MES_OP_1_00",
      "Text": "<FACE_DUNHILL><POS_RIGHT><FACE_NORMAL>\r\nさぁ、着いたぞ。\nここが、<RED>やまびこの町</RED>だ。"
    },
    {
      "VardId": "MES_OP_1_01",
      "Text": "<FACE_DUNHILL><POS_RIGHT><FACE_NORMAL>\r\nご両親の手紙には、\n色々書いてあったよ。\n<PAGE>\nキミは大人になったお祝いに、\n昔、ご先祖様がやっていた牧場の土地を\nお父さんから譲り受けたそうだね？"
    },
    {
      "VardId": "MES_OP_1_02",
      "Text": "<FACE_DUNHILL><POS_RIGHT><FACE_NORMAL>\r\nその土地はね、\n元々はキミのお父さんが継いで、\n牧場を経営するためのものだったんだよ。\n<PAGE>\nだけど、キミのお母さんと結婚するために\n他の町に引っ越すことになってね。\n結局、継がなかったという訳さ。"
    },
    {
      "VardId": "MES_OP_1_03",
      "Text": "<FACE_DUNHILL><POS_RIGHT><FACE_ROUGH>\r\nそれでも、キミのお父さんは\nこの土地を手放したくないと言って、\n時々、町へ手入れに来ていたんだ。\n<PAGE>\nそれぐらい、\nこの土地に愛着があったそうだよ。"
    },
    {
      "VardId": "MES_OP_1_04",
      "Text": "<FACE_DUNHILL><POS_RIGHT><FACE_NORMAL>\r\nだから、今回その土地に\nキミが暮らしてくれることになって\nすごくうれしいと言っていたよ。\n<PAGE>\nあとは、キミの事をよろしく頼むって\n書かれていたよ。"
    },
    {
      "VardId": "MES_OP_1_05",
      "Text": "<FACE_DUNHILL><POS_RIGHT><FACE_ROUGH>\r\nキミのご両親からのお願いとあれば、\n喜んで引き受けさせてもらうよ。\nまぁ、こっちにも事情があるんだけどな…。"
    },
    {
      "VardId": "MES_OP_1_06",
      "Text": "<FACE_DUNHILL><POS_RIGHT><FACE_NORMAL>\r\nそれは、おいおい話していくとして、\nまずは助けてくれたお礼に、\n食事をごちそうさせてくれないか？\n<PAGE>\nここまで来るのは、大変だっただろう。\nオレの家で少し身体を休めるといい。\nじゃあ、行こうか。"
    },
    {
      "VardId": "MES_OP_1_07",
      "Text": "<FACE_DUNHILL><POS_RIGHT><FACE_NORMAL>\r\nここがオレの家だよ。\n何か困った事があったら、ここに来てくれ。\n出来る限りのことはするよ。"
    },
    {
      "VardId": "MES_OP_1_08",
      "Text": "<FACE_DUNHILL><POS_RIGHT><FACE_ROUGH>\r\n食事をごちそうするついでに、\n<RED>体力</RED>と<RED>体調</RED>についても説明するよ。\nさあ、中へ入ろう。"
    }
  ]
}