{
  "Date": "2016-06-25T01:44:52.6344812+07:00",
  "Author": "BokujoMessage4 JSON generated files",
  "Content": [
    {
      "VardId": "MES_SHOP_BEFORE_OPEN",
      "Text": "<NAME_MOB_CHAHA>\r\n今日も浜茶屋に行くとするワイ。\nワシの日課なんじゃぞイ。"
    },
    {
      "VardId": "MES_SHOP_BREAK",
      "Text": "<NAME_MOB_CHAHA>\r\n今日も浜茶屋に行くとするワイ。\nワシの日課なんじゃぞイ。"
    },
    {
      "VardId": "MES_SHOP_CLOSED",
      "Text": "<NAME_MOB_CHAHA>\r\n今日も浜茶屋に行くとするワイ。\nワシの日課なんじゃぞイ。"
    },
    {
      "VardId": "MES_WORKING_A",
      "Text": "<NAME_MOB_CHAHA>\r\n今日も浜茶屋に行くとするワイ。\nワシの日課なんじゃぞイ。"
    },
    {
      "VardId": "MES_BEFORE_WORKING_A",
      "Text": "<NAME_MOB_CHAHA>\r\n今日も浜茶屋に行くとするワイ。\nワシの日課なんじゃぞイ。"
    },
    {
      "VardId": "MES_AFTER_WORKING_A",
      "Text": "<NAME_MOB_CHAHA>\r\n今日も浜茶屋に行くとするワイ。\nワシの日課なんじゃぞイ。"
    },
    {
      "VardId": "MES_WORKING_J",
      "Text": "<NAME_MOB_CHAHA>\r\n今日も浜茶屋に行くとするワイ。\nワシの日課なんじゃぞイ。"
    },
    {
      "VardId": "MES_BEFORE_WORKING_J",
      "Text": "<NAME_MOB_CHAHA>\r\n今日も浜茶屋に行くとするワイ。\nワシの日課なんじゃぞイ。"
    },
    {
      "VardId": "MES_AFTER_WORKING_J",
      "Text": "<NAME_MOB_CHAHA>\r\n今日も浜茶屋に行くとするワイ。\nワシの日課なんじゃぞイ。"
    },
    {
      "VardId": "MES_WORKING_S",
      "Text": "<NAME_MOB_CHAHA>\r\n今日も浜茶屋に行くとするワイ。\nワシの日課なんじゃぞイ。"
    },
    {
      "VardId": "MES_BEFORE_WORKING_S",
      "Text": "<NAME_MOB_CHAHA>\r\n今日も浜茶屋に行くとするワイ。\nワシの日課なんじゃぞイ。"
    },
    {
      "VardId": "MES_AFTER_WORKING_S",
      "Text": "<NAME_MOB_CHAHA>\r\n今日も浜茶屋に行くとするワイ。\nワシの日課なんじゃぞイ。"
    },
    {
      "VardId": "MES_PLACE_00",
      "Text": "<NAME_MOB_CHAHA>\r\n今日も浜茶屋に行くとするワイ。\nワシの日課なんじゃぞイ。"
    },
    {
      "VardId": "MES_PLACE_01",
      "Text": "<NAME_MOB_CHAHA>\r\n今日も浜茶屋に行くとするワイ。\nワシの日課なんじゃぞイ。"
    },
    {
      "VardId": "MES_PARODY_00",
      "Text": "<NAME_MOB_CHAHA>\r\n今日も浜茶屋に行くとするワイ。\nワシの日課なんじゃぞイ。"
    },
    {
      "VardId": "MES_PARODY_01",
      "Text": "<NAME_MOB_CHAHA>\r\n今日も浜茶屋に行くとするワイ。\nワシの日課なんじゃぞイ。"
    },
    {
      "VardId": "MES_PARODY_02",
      "Text": "<NAME_MOB_CHAHA>\r\n今日も浜茶屋に行くとするワイ。\nワシの日課なんじゃぞイ。"
    },
    {
      "VardId": "MES_PARODY_03",
      "Text": "<NAME_MOB_CHAHA>\r\n今日も浜茶屋に行くとするワイ。\nワシの日課なんじゃぞイ。"
    },
    {
      "VardId": "MES_WORKING_00",
      "Text": "<NAME_MOB_CHAHA>\r\nうーむ、ウーム……\nいつ見てもきゃわゆいノ〜<RED>∀</RED>"
    },
    {
      "VardId": "MES_WORKING_01",
      "Text": "<NAME_MOB_CHAHA>\r\n今日もここで食事ジャ。\nワシの日課なんじゃぞイ。"
    },
    {
      "VardId": "MES_NOT_WORKING_00",
      "Text": "<NAME_MOB_CHAHA>\r\n浜茶屋の二人の娘のことを考えると、\nなんだか力がみなぎってくるんジャ〜♪"
    },
    {
      "VardId": "MES_NOT_WORKING_01",
      "Text": "<NAME_MOB_CHAHA>\r\nワシの楽しみは、\nなんといっても巫女さんじゃヨ<RED>∀</RED>"
    },
    {
      "VardId": "MES_NOT_WORKING_02",
      "Text": "<NAME_MOB_CHAHA>\r\nオヌシ、イゥカちゃんとシゥカちゃん\nどっちのほうが好みなんジャ？\nワシは、長年決めかねとル。"
    },
    {
      "VardId": "MES_NOT_WORKING_03",
      "Text": "<NAME_MOB_CHAHA>\r\nクールかわいいイゥカちゃんと、\nほんわか天然シゥカちゃん……\nうーん、やっぱり決められんワイ！"
    },
    {
      "VardId": "MES_TALK_00",
      "Text": "<NAME_MOB_CHAHA>\r\n今日も浜茶屋に行くとするワイ。\nワシの日課なんじゃぞイ。"
    },
    {
      "VardId": "MES_TALK_01",
      "Text": "<NAME_MOB_CHAHA>\r\n今日も浜茶屋に行くとするワイ。\nワシの日課なんじゃぞイ。"
    }
  ]
}