{
  "Date": "2016-06-10T19:21:59.1347071+07:00",
  "Author": "BokujoMessage4 JSON generated files",
  "Content": [
    {
      "VardId": "MES_SYSTEM_STUDIO_01",
      "Text": "<FACE_KAISER><POS_RIGHT><FACE_NORMAL>\nSalut ! On m'a dit que tu voulais construire\nun genre d'atelier, alors je suis venu\nte donner un coup d'main."
    },
    {
      "VardId": "MES_SYSTEM_STUDIO_02",
      "Text": "<FACE_KAISER><POS_RIGHT><FACE_NORMAL>\nAllez, au boulot ! J'vais te filer quelques tuyaux\nau fur et à mesure, alors fais ce que j'te dis,\ncompris ?"
    },
    {
      "VardId": "MES_SYSTEM_STUDIO_03",
      "Text": "<FACE_KAISER><POS_RIGHT><FACE_NORMAL>\nBien joué ! C'est du beau travail que tu as fait là.\n<PAGE>\nBref, c'est l'heure de rentrer chez moi."
    },
    {
      "VardId": "MES_SYSTEM_STUDIO_04",
      "Text": "Youpi ! Mon atelier est enfin terminé !\nAllons voir à l'intérieur !"
    }
  ]
}