{
  "Date": "2016-06-10T19:21:14.6479566+07:00",
  "Author": "BokujoMessage4 JSON generated files",
  "Content": [
    {
      "VardId": "hat_000",
      "Text": "Farmerhut<m>"
    },
    {
      "VardId": "hat_001",
      "Text": "Kopftuch<n>"
    },
    {
      "VardId": "hat_500",
      "Text": "Strohhut<m>"
    },
    {
      "VardId": "hat_501",
      "Text": "Zylinder<m>"
    },
    {
      "VardId": "hat_502",
      "Text": "Blaue Zeitungsjungen-Mütze<f>"
    },
    {
      "VardId": "hat_503",
      "Text": "Schwarzer Tirolerhut<m>"
    },
    {
      "VardId": "hat_504",
      "Text": "Hüttenland-Hut<m>"
    },
    {
      "VardId": "hat_505",
      "Text": "Cowgirl-Hut<m>"
    },
    {
      "VardId": "hat_506",
      "Text": "Konischer Hut<m>"
    },
    {
      "VardId": "hat_507",
      "Text": "Blumen-Haarklammer<f>"
    },
    {
      "VardId": "hat_508",
      "Text": "Rosa Mini-Hut<m>"
    },
    {
      "VardId": "hat_509",
      "Text": "Brauner Cowboyhut<m>"
    },
    {
      "VardId": "hat_511",
      "Text": "Uschanka<f>"
    },
    {
      "VardId": "hat_512",
      "Text": "Gothic-Haarband<n>"
    },
    {
      "VardId": "hat_513",
      "Text": "Dienstmädchen-Haarschmuck<m>"
    },
    {
      "VardId": "hat_514",
      "Text": "Strickmütze<f>"
    },
    {
      "VardId": "hat_515",
      "Text": "Barett<n>"
    },
    {
      "VardId": "hat_516",
      "Text": "Kochmütze<f>"
    },
    {
      "VardId": "hat_517",
      "Text": "Hexenhut<m>"
    },
    {
      "VardId": "hat_518",
      "Text": "Seltsam vertrauter Hut<m>"
    },
    {
      "VardId": "hat_519",
      "Text": "Schwarzer Katzen-Haarreif<m>"
    },
    {
      "VardId": "hat_520",
      "Text": "Brauner Hunde-Haarreif<m>"
    },
    {
      "VardId": "hat_521",
      "Text": "Matrosenmütze<f>"
    },
    {
      "VardId": "hat_522",
      "Text": "Schutzbrille<f>"
    },
    {
      "VardId": "hat_523",
      "Text": "Krone<f>"
    },
    {
      "VardId": "hat_524",
      "Text": "Kopfhörer<m>"
    },
    {
      "VardId": "hat_525",
      "Text": "Prächtiger Hut<m>"
    },
    {
      "VardId": "hat_708",
      "Text": "Katzenmaske<f>"
    },
    {
      "VardId": "hat_709",
      "Text": "Hundemaske<f>"
    },
    {
      "VardId": "hat_710",
      "Text": "Bärenmaske<f>"
    },
    {
      "VardId": "hat_711",
      "Text": "Pandamaske<f>"
    },
    {
      "VardId": "hat_716",
      "Text": "Pinguinmaske<f>"
    },
    {
      "VardId": "hat_717",
      "Text": "Ritterhelm<m>"
    },
    {
      "VardId": "hat_526",
      "Text": "Rote Zeitungsjungen-Mütze<f>"
    },
    {
      "VardId": "hat_527",
      "Text": "Grüne Zeitungsjungen-Mütze<f>"
    },
    {
      "VardId": "hat_528",
      "Text": "Schwarze Zeitungsjungen-Mütze<f>"
    },
    {
      "VardId": "hat_529",
      "Text": "Weiße Zeitungsjungen-Mütze<f>"
    },
    {
      "VardId": "hat_530",
      "Text": "Grüner Tirolerhut<m>"
    },
    {
      "VardId": "hat_531",
      "Text": "Roter Tirolerhut<m>"
    },
    {
      "VardId": "hat_532",
      "Text": "Blauer Tirolerhut<m>"
    },
    {
      "VardId": "hat_533",
      "Text": "Blauer Mini-Hut<m>"
    },
    {
      "VardId": "hat_534",
      "Text": "Gelber Mini-Hut<m>"
    },
    {
      "VardId": "hat_535",
      "Text": "Lila Mini-Hut<m>"
    },
    {
      "VardId": "hat_536",
      "Text": "Roter Cowboy-Hut<m>"
    },
    {
      "VardId": "hat_537",
      "Text": "Blauer Cowboy-Hut<m>"
    },
    {
      "VardId": "hat_538",
      "Text": "Schwarzer Cowboy-Hut<m>"
    },
    {
      "VardId": "hat_539",
      "Text": "Weißer Katzen-Haarreif<m>"
    },
    {
      "VardId": "hat_540",
      "Text": "Weißer Hunde-Haarreif<m>"
    }
  ]
}