{
  "Date": "2016-06-06T19:37:50.2552163+07:00",
  "Author": "BokujoMessage4 JSON generated files",
  "Content": [
    {
      "VardId": "MES_STORY_FAST_SHOP_01",
      "Text": "<FACE_OTMAR><POS_LEFT><FACE_NORMAL>\r\nおやおや、初めて見る顔じゃの〜。\n<PAGE>\nほう、あの牧場に来た子かい。\nよろしくの〜。\n<PAGE>\nわしの名前は<BLUE>オットマー</BLUE>というんじゃ。\nここの雑貨屋を経営しておる。\n<PAGE>\n雑貨屋といっても、たいしたもんは\n売っておらんが…。まぁ、牧場をする上で\n役に立つものもあるじゃろ。\n<PAGE>\nよかったら、営業時間中に\nカウンターから話しかけて、\n商品をみていっておくれ。"
    },
    {
      "VardId": "MES_STORY_FAST_SHOP_02",
      "Text": "<FACE_OTMAR><POS_LEFT><FACE_NORMAL>\r\n<MYNAME>、どうも。\nうちの雑貨屋によく来てくれたの〜。\n<PAGE>\n雑貨屋といっても、たいしたもんは\n売っておらんが…。まぁ、牧場をする上で\n役に立つものもあるじゃろ。\n<PAGE>\nよかったら、営業時間中に\nカウンターから話しかけて、\n商品をみていっておくれ。"
    }
  ]
}